Metadata-Version: 2.1
Name: py-entity-linking
Version: 0.1.5
Summary: A lightweight library for entity linking in English
Author: Nikolas Kapralos
Requires-Python: >=3.10
Requires-Dist: numpy==1.26.4
Requires-Dist: SPARQLWrapper==2.0.0
Requires-Dist: sentence_transformers==3.1.1
Requires-Dist: aiohttp==3.9.5
Requires-Dist: openai==1.55.3
Requires-Dist: httpx==0.27.2
Requires-Dist: beautifulsoup4==4.12.2
Requires-Dist: nest_asyncio==1.5.8
